gns3_webclient_pack/__init__.py
gns3_webclient_pack/application.py
gns3_webclient_pack/launcher.py
gns3_webclient_pack/launcher_error.py
gns3_webclient_pack/local_config.py
gns3_webclient_pack/main.py
gns3_webclient_pack/main_window.py
gns3_webclient_pack/pcap_stream.py
gns3_webclient_pack/settings.py
gns3_webclient_pack/version.py
gns3_webclient_pack/dialogs/__init__.py
gns3_webclient_pack/dialogs/about_dialog.py
gns3_webclient_pack/dialogs/command_dialog.py
gns3_webclient_pack/dialogs/login_dialog.py
gns3_webclient_pack/linux/applications/gns3-webclient-config.desktop
gns3_webclient_pack/linux/applications/gns3-webclient-launcher.desktop
gns3_webclient_pack/linux/icons/hicolor/16x16/apps/gns3_webclient.png
gns3_webclient_pack/linux/icons/hicolor/32x32/apps/gns3_webclient.png
gns3_webclient_pack/linux/icons/hicolor/48x48/apps/gns3_webclient.png
gns3_webclient_pack/linux/icons/hicolor/scalable/apps/gns3_webclient.svg
gns3_webclient_pack/qt/__init__.py
gns3_webclient_pack/ui/__init__.py
gns3_webclient_pack/ui/about_dialog.ui
gns3_webclient_pack/ui/about_dialog_ui.py
gns3_webclient_pack/ui/command_dialog.ui
gns3_webclient_pack/ui/command_dialog_ui.py
gns3_webclient_pack/ui/login_dialog.ui
gns3_webclient_pack/ui/login_dialog_ui.py
gns3_webclient_pack/ui/main_window.ui
gns3_webclient_pack/ui/main_window_ui.py
gns3_webclient_pack/ui/resources_rc.py
gns3_webclient_pack/utils/__init__.py
gns3_webclient_pack/utils/bring_to_front.py
gns3_webclient_pack/utils/get_resource.py
gns3_webclient_pack/utils/install_mime_types.py
gns3_webclient_pack-1.0.0b6.dist-info/AUTHORS
gns3_webclient_pack-1.0.0b6.dist-info/LICENSE
gns3_webclient_pack-1.0.0b6.dist-info/METADATA
gns3_webclient_pack-1.0.0b6.dist-info/WHEEL
gns3_webclient_pack-1.0.0b6.dist-info/entry_points.txt
gns3_webclient_pack-1.0.0b6.dist-info/top_level.txt
gns3_webclient_pack-1.0.0b6.dist-info/RECORD
