Metadata-Version: 2.1
Name: gns3-webclient-pack
Version: 1.0.0b6
Summary: GNS3 WebClient pack to use with the GNS3 web interface
Author-email: Jeremy Grossmann <developers@gns3.com>
License: GNU GENERAL PUBLIC LICENSE
Project-URL: Homepage, http://gns3.com
Project-URL: Repository, http://github.com/GNS3/gns3-webclient-pack
Project-URL: Bug tracker, http://github.com/GNS3/gns3-webclient-pack/issues
Classifier: Development Status :: 4 - Beta
Classifier: Environment :: X11 Applications :: Qt
Classifier: Intended Audience :: Information Technology
Classifier: Topic :: System :: Networking
Classifier: License :: OSI Approved :: GNU General Public License v3 (GPLv3)
Classifier: Natural Language :: English
Classifier: Operating System :: POSIX
Classifier: Operating System :: MacOS :: MacOS X
Classifier: Operating System :: Microsoft :: Windows
Classifier: Programming Language :: Python :: 3
Classifier: Programming Language :: Python :: 3.4
Classifier: Programming Language :: Python :: 3.5
Classifier: Programming Language :: Python :: 3.6
Classifier: Programming Language :: Python :: 3.7
Classifier: Programming Language :: Python :: 3.8
Classifier: Programming Language :: Python :: 3.9
Classifier: Programming Language :: Python :: 3.10
Classifier: Programming Language :: Python :: 3.11
Classifier: Programming Language :: Python :: 3.12
Classifier: Programming Language :: Python :: Implementation :: CPython
Requires-Python: >=3.4
License-File: LICENSE
License-File: AUTHORS
Requires-Dist: distro ==1.8.0
Requires-Dist: psutil ==5.9.6
Requires-Dist: importlib-resources >=1.3 ; python_version <= "3.9"
Requires-Dist: truststore >=0.8.0 ; python_version >= "3.10"
Provides-Extra: dev
Requires-Dist: pep8 ==1.7.1 ; extra == 'dev'
Requires-Dist: pytest-qt ==4.2.0 ; extra == 'dev'
Requires-Dist: pytest ==7.0.1 ; (python_version < "3.7") and extra == 'dev'
Requires-Dist: pytest ==7.2.0 ; (python_version >= "3.7") and extra == 'dev'
